{
	"info": {
		"_postman_id": "7c58f8a3-ce20-498e-8247-9707ef77501a",
		"name": "file_upload",
		"schema": "https://schema.getpostman.com/json/collection/v2.1.0/collection.json",
		"_exporter_id": "30711162"
	},
	"item": [
		{
			"name": "New Request",
			"request": {
				"method": "POST",
				"header": [],
				"body": {
					"mode": "formdata",
					"formdata": [
						{
							"key": "",
							"type": "file",
							"src": "/C:/AutoamtionPractice/postman_files/sample_file.txt"
						}
					]
				},
				"url": {
					"raw": "https://postman-echo.com/post",
					"protocol": "https",
					"host": [
						"postman-echo",
						"com"
					],
					"path": [
						"post"
					]
				}
			},
			"response": []
		}
	]
}